mProfile
