Metadata-Version: 2.1
Name: mProfile-mut
Version: 2.1
Summary: nucleotide-resolution mutation calling
Home-page: https://github.com/aldob/mProfile
Author: Aldo Saleh Bader
License: UNKNOWN
Download-URL: https://github.com/aldob/mProfile/archive/v1.4.tar.gz
Platform: UNKNOWN
